{
  "BurstVersion": "12fd8c57-ac57-41e8-88f3-e2a61ac3563b",
  "Assemblies": [
    {
      "FullName": "Unity.Burst, Version=0.0.0.0, Culture=neutral, PublicKeyToken=null",
      "LastWriteTime": "2021-12-21T04:50:57.1659341Z"
    },
    {
      "FullName": "netstandard, Version=2.0.0.0, Culture=neutral, PublicKeyToken=cc7b13ffcd2ddd51",
      "LastWriteTime": "2021-11-23T01:42:22Z"
    },
    {
      "FullName": "mscorlib, Version=4.0.0.0, Culture=neutral, PublicKeyToken=b77a5c561934e089",
      "LastWriteTime": "2021-11-23T01:42:22Z"
    },
    {
      "FullName": "UnityEngine.CoreModule, Version=0.0.0.0, Culture=neutral, PublicKeyToken=null",
      "LastWriteTime": "2021-11-23T01:47:18Z"
    },
    {
      "FullName": "Unity.Barracuda, Version=2.0.0.0, Culture=neutral, PublicKeyToken=null",
      "LastWriteTime": "2021-12-21T04:50:59.5749333Z"
    },
    {
      "FullName": "mscorlib, Version=2.0.0.0, Culture=neutral, PublicKeyToken=b77a5c561934e089",
      "LastWriteTime": "2021-11-23T01:42:22Z"
    },
    {
      "FullName": "Unity.Mathematics, Version=1.0.0.0, Culture=neutral, PublicKeyToken=null",
      "LastWriteTime": "2021-12-21T04:50:58.4689335Z"
    }
  ],
  "Functions": [
    {
      "FullName": "System.Int32 Unity.Burst.Intrinsics.X86::DoGetCSRTrampoline()",
      "ModuleOptionsHash": 8794384452606821980,
      "ModuleHash": "a2f0be605929b1597c858b334c4031f6",
      "LinkName": "CDCA4A5193BE5947",
      "AssemblyDependencyIndices": [
        0,
        1,
        2
      ]
    },
    {
      "FullName": "System.Void Unity.Burst.Intrinsics.X86::DoSetCSRTrampoline(System.Int32)",
      "ModuleOptionsHash": 8794384452606821980,
      "ModuleHash": "9437e8b2aca53727f302d25ed69117e3",
      "LinkName": "801E9A000BB37B05",
      "AssemblyDependencyIndices": [
        0,
        1,
        2
      ]
    },
    {
      "FullName": "System.Void Unity.Jobs.IJobExtensions/JobStruct`1<Unity.Barracuda.BurstCPUOps/CopyJob>::Execute(T&,System.IntPtr,System.IntPtr,Unity.Jobs.LowLevel.Unsafe.JobRanges&,System.Int32)",
      "ModuleOptionsHash": 13433243922868730427,
      "ModuleHash": "40541d99bcc7f350050e7a39dba74771",
      "LinkName": "B679BCA8E17D18D0",
      "AssemblyDependencyIndices": [
        3,
        4,
        5,
        1,
        2
      ]
    },
    {
      "FullName": "System.Void Unity.Jobs.IJobExtensions/JobStruct`1<Unity.Barracuda.BurstCPUOps/VectorBroadcastJob>::Execute(T&,System.IntPtr,System.IntPtr,Unity.Jobs.LowLevel.Unsafe.JobRanges&,System.Int32)",
      "ModuleOptionsHash": 13433243922868730427,
      "ModuleHash": "85d48401bb27bc2633c30670c7a93433",
      "LinkName": "D5A0000F5DA19291",
      "AssemblyDependencyIndices": [
        3,
        4,
        5,
        1,
        2
      ]
    },
    {
      "FullName": "System.Void Unity.Jobs.IJobParallelForExtensions/ParallelForJobStruct`1<Unity.Barracuda.BurstCPUOps/MatrixMultiplyJob>::Execute(T&,System.IntPtr,System.IntPtr,Unity.Jobs.LowLevel.Unsafe.JobRanges&,System.Int32)",
      "ModuleOptionsHash": 13433243922868730427,
      "ModuleHash": "88e2a5fa3e312313454d90e7e7004a63",
      "LinkName": "8D6F6DCD15B44F73",
      "AssemblyDependencyIndices": [
        3,
        4,
        5,
        1,
        2
      ]
    },
    {
      "FullName": "System.Void Unity.Jobs.IJobParallelForExtensions/ParallelForJobStruct`1<Unity.Barracuda.BurstCPUOps/SwishJob>::Execute(T&,System.IntPtr,System.IntPtr,Unity.Jobs.LowLevel.Unsafe.JobRanges&,System.Int32)",
      "ModuleOptionsHash": 8794384452606821980,
      "ModuleHash": "fd82ee46c355a1cfcd9bb0826d735395",
      "LinkName": "096BF73F62FE1FA1",
      "AssemblyDependencyIndices": [
        3,
        4,
        5,
        1,
        2,
        6
      ]
    },
    {
      "FullName": "System.Void Unity.Jobs.IJobParallelForExtensions/ParallelForJobStruct`1<Unity.Barracuda.BurstCPUOps/GenericSliceJob>::Execute(T&,System.IntPtr,System.IntPtr,Unity.Jobs.LowLevel.Unsafe.JobRanges&,System.Int32)",
      "ModuleOptionsHash": 13433243922868730427,
      "ModuleHash": "2dea305258875cbe5ddda22af3deba01",
      "LinkName": "7B3D1FE68C9CBBA0",
      "AssemblyDependencyIndices": [
        3,
        4,
        5,
        1,
        2
      ]
    },
    {
      "FullName": "System.Void Unity.Jobs.IJobParallelForExtensions/ParallelForJobStruct`1<Unity.Barracuda.BurstCPUOps/ReduceMaxJob>::Execute(T&,System.IntPtr,System.IntPtr,Unity.Jobs.LowLevel.Unsafe.JobRanges&,System.Int32)",
      "ModuleOptionsHash": 13433243922868730427,
      "ModuleHash": "08904ba8740307fc17e83d37dad09b3a",
      "LinkName": "BAF2F998A757C0EB",
      "AssemblyDependencyIndices": [
        3,
        4,
        5,
        1,
        2,
        6
      ]
    },
    {
      "FullName": "System.Void Unity.Jobs.IJobParallelForExtensions/ParallelForJobStruct`1<Unity.Barracuda.BurstCPUOps/ExpBiasReduceJob>::Execute(T&,System.IntPtr,System.IntPtr,Unity.Jobs.LowLevel.Unsafe.JobRanges&,System.Int32)",
      "ModuleOptionsHash": 13433243922868730427,
      "ModuleHash": "706fe60be920b319e5b6affd1fad7c7f",
      "LinkName": "191C49F536466F62",
      "AssemblyDependencyIndices": [
        3,
        4,
        5,
        1,
        2,
        6
      ]
    },
    {
      "FullName": "System.Void Unity.Jobs.IJobParallelForExtensions/ParallelForJobStruct`1<Unity.Barracuda.BurstCPUOps/SoftmaxEndJob>::Execute(T&,System.IntPtr,System.IntPtr,Unity.Jobs.LowLevel.Unsafe.JobRanges&,System.Int32)",
      "ModuleOptionsHash": 8794384452606821980,
      "ModuleHash": "9340b0305fd8320ee789c6a7c4d77d4c",
      "LinkName": "A0D2BFE049A8C470",
      "AssemblyDependencyIndices": [
        3,
        4,
        5,
        1,
        2,
        6
      ]
    },
    {
      "FullName": "System.Void Unity.Jobs.IJobExtensions/JobStruct`1<Unity.Barracuda.BurstCPUOps/MemFreeJob>::Execute(T&,System.IntPtr,System.IntPtr,Unity.Jobs.LowLevel.Unsafe.JobRanges&,System.Int32)",
      "ModuleOptionsHash": 13433243922868730427,
      "ModuleHash": "16a747fb7c26540b248031650fd5594e",
      "LinkName": "762F76951C50D82E",
      "AssemblyDependencyIndices": [
        3,
        4,
        5,
        1,
        2
      ]
    },
    {
      "FullName": "System.Void Unity.Jobs.IJobParallelForExtensions/ParallelForJobStruct`1<Unity.Barracuda.BurstCPUOps/ScalarBroadcastAddJob>::Execute(T&,System.IntPtr,System.IntPtr,Unity.Jobs.LowLevel.Unsafe.JobRanges&,System.Int32)",
      "ModuleOptionsHash": 13433243922868730427,
      "ModuleHash": "fdade1e11eb6877e6c90f70bb661213d",
      "LinkName": "0C2FED748A17D8BA",
      "AssemblyDependencyIndices": [
        3,
        4,
        5,
        1,
        2
      ]
    },
    {
      "FullName": "System.Void Unity.Jobs.IJobParallelForExtensions/ParallelForJobStruct`1<Unity.Barracuda.BurstCPUOps/BroadcastMulJob>::Execute(T&,System.IntPtr,System.IntPtr,Unity.Jobs.LowLevel.Unsafe.JobRanges&,System.Int32)",
      "ModuleOptionsHash": 13433243922868730427,
      "ModuleHash": "1dfc05dd2ad4159f6f927c4fe247e9c1",
      "LinkName": "81B8E51DCAD87F47",
      "AssemblyDependencyIndices": [
        3,
        4,
        5,
        1,
        2
      ]
    },
    {
      "FullName": "System.Void Unity.Jobs.IJobParallelForExtensions/ParallelForJobStruct`1<Unity.Barracuda.BurstCPUOps/ReduceSumJob>::Execute(T&,System.IntPtr,System.IntPtr,Unity.Jobs.LowLevel.Unsafe.JobRanges&,System.Int32)",
      "ModuleOptionsHash": 13433243922868730427,
      "ModuleHash": "a98e18db900145b7f9bd1c4436915205",
      "LinkName": "FAF64C98A3BBE3F9",
      "AssemblyDependencyIndices": [
        3,
        4,
        5,
        1,
        2
      ]
    },
    {
      "FullName": "System.Void Unity.Jobs.IJobParallelForExtensions/ParallelForJobStruct`1<Unity.Barracuda.BurstCPUOps/ScalarBroadcastDivJob>::Execute(T&,System.IntPtr,System.IntPtr,Unity.Jobs.LowLevel.Unsafe.JobRanges&,System.Int32)",
      "ModuleOptionsHash": 13433243922868730427,
      "ModuleHash": "d3387ed0210c152b2227b67e11f7ecc9",
      "LinkName": "AE9993A767C1986F",
      "AssemblyDependencyIndices": [
        3,
        4,
        5,
        1,
        2
      ]
    },
    {
      "FullName": "System.Void Unity.Jobs.IJobParallelForExtensions/ParallelForJobStruct`1<Unity.Barracuda.BurstCPUOps/LogJob>::Execute(T&,System.IntPtr,System.IntPtr,Unity.Jobs.LowLevel.Unsafe.JobRanges&,System.Int32)",
      "ModuleOptionsHash": 8794384452606821980,
      "ModuleHash": "8598163ad25d8bde3e54c08793e68f3b",
      "LinkName": "AEB3E7DD999C9405",
      "AssemblyDependencyIndices": [
        3,
        4,
        5,
        1,
        2,
        6
      ]
    },
    {
      "FullName": "System.Void Unity.Jobs.IJobExtensions/JobStruct`1<Unity.Barracuda.BurstCPUOps/CopyStrideJob>::Execute(T&,System.IntPtr,System.IntPtr,Unity.Jobs.LowLevel.Unsafe.JobRanges&,System.Int32)",
      "ModuleOptionsHash": 13433243922868730427,
      "ModuleHash": "5d34bbfc406eb98a95ff669c35914682",
      "LinkName": "94CA01341FF17CF3",
      "AssemblyDependencyIndices": [
        3,
        4,
        5,
        1,
        2
      ]
    }
  ]
}